datakund_scraper
